{
  "cli": {
    "version": ">= 5.9.0"
  },
  "build": {
    "development": {
      "developmentClient": true,
      "distribution": "internal",
      "android": {
        "gradleCommand": ":app:assembleDebug"
      }
    },
    "preview": {
      "distribution": "internal",
      "android": {
        "buildType": "apk"
      },
      "ios": {
        "simulator": true
      },
      "env": {
        "YARN_IGNORE_ENGINES": "1"
      }
    },
    "production": {
      "android": {
        "buildType": "apk"
      },
      "env": {
        "YARN_IGNORE_ENGINES": "1"
      }
    }
  },
  "submit": {
    "production": {}
  }
}